metacontroller_api/__init__.py
metacontroller_api/controllers.py
metacontroller_api/py.typed
metacontroller_api/types.py
metacontroller_api/contrib/__init__.py
metacontroller_api/contrib/flask.py
metacontroller_api-0.3.0.dist-info/METADATA
metacontroller_api-0.3.0.dist-info/WHEEL
metacontroller_api-0.3.0.dist-info/RECORD
