Metadata-Version: 2.4
Name: metacontroller-api
Version: 0.3.0
Summary: Convenient package for implement Kubernetes controllers using Metacontroller.
Author-email: Niklas Rosenstein <rosensteinniklas@gmail.com>
Requires-Python: >=3.13
Requires-Dist: flask>=3.1.0
Requires-Dist: loguru>=0.7.3
